[
  {
    "ticker": "ETH-USD",
    "nombre": "Ethereum",
    "precio_usd": 2348.645,
    "precio_mxn": 40396.69,
    "mape_nd": 14.1,
    "señal_1d": "VENTA",
    "cambio_1d": -11.93,
    "color_1d": "#ef4444",
    "señal_5d": "VENTA",
    "cambio_5d": -58.37,
    "color_5d": "#ef4444",
    "señal_10d": "VENTA",
    "cambio_10d": -95.57,
    "color_10d": "#ef4444",
    "score": 4.6366,
    "img": "ETH_USD.png",
    "es_cripto": true
  },
  {
    "ticker": "BNB-USD",
    "nombre": "Binance Coin",
    "precio_usd": 635.5834,
    "precio_mxn": 10932.03,
    "mape_nd": 21.53,
    "señal_1d": "VENTA",
    "cambio_1d": -27.86,
    "color_1d": "#ef4444",
    "señal_5d": "VENTA",
    "cambio_5d": -32.43,
    "color_5d": "#ef4444",
    "señal_10d": "VENTA",
    "cambio_10d": -60.06,
    "color_10d": "#ef4444",
    "score": 3.1072,
    "img": "BNB_USD.png",
    "es_cripto": true
  },
  {
    "ticker": "BTC-USD",
    "nombre": "Bitcoin",
    "precio_usd": 75152.1328,
    "precio_mxn": 1292616.68,
    "mape_nd": 21.7,
    "señal_1d": "VENTA",
    "cambio_1d": -20.85,
    "color_1d": "#ef4444",
    "señal_5d": "VENTA",
    "cambio_5d": -41.99,
    "color_5d": "#ef4444",
    "señal_10d": "VENTA",
    "cambio_10d": -77.2,
    "color_10d": "#ef4444",
    "score": 3.0838,
    "img": "BTC_USD.png",
    "es_cripto": true
  },
  {
    "ticker": "SOL-USD",
    "nombre": "Solana",
    "precio_usd": 88.9942,
    "precio_mxn": 1530.7,
    "mape_nd": 49.44,
    "señal_1d": "VENTA",
    "cambio_1d": -127.12,
    "color_1d": "#ef4444",
    "señal_5d": "VENTA",
    "cambio_5d": -168.91,
    "color_5d": "#ef4444",
    "señal_10d": "VENTA",
    "cambio_10d": -219.67,
    "color_10d": "#ef4444",
    "score": 1.3877,
    "img": "SOL_USD.png",
    "es_cripto": true
  },
  {
    "ticker": "ADA-USD",
    "nombre": "Cardano",
    "precio_usd": 0.2592,
    "precio_mxn": 4.46,
    "mape_nd": 137.52,
    "señal_1d": "COMPRA",
    "cambio_1d": 85.88,
    "color_1d": "#22c55e",
    "señal_5d": "COMPRA",
    "cambio_5d": 41.65,
    "color_5d": "#22c55e",
    "señal_10d": "COMPRA",
    "cambio_10d": 42.6,
    "color_10d": "#22c55e",
    "score": 0.9385,
    "img": "ADA_USD.png",
    "es_cripto": true
  },
  {
    "ticker": "AAPL",
    "nombre": "Apple",
    "precio_usd": 263.4,
    "precio_mxn": 4530.48,
    "mape_nd": 11.2,
    "señal_1d": "VENTA",
    "cambio_1d": -18.05,
    "color_1d": "#ef4444",
    "señal_5d": "VENTA",
    "cambio_5d": -20.82,
    "color_5d": "#ef4444",
    "señal_10d": "VENTA",
    "cambio_10d": -18.25,
    "color_10d": "#ef4444",
    "score": 5.7356,
    "img": "AAPL.png",
    "es_cripto": false
  },
  {
    "ticker": "GOOGL",
    "nombre": "Alphabet (Google)",
    "precio_usd": 336.02,
    "precio_mxn": 5779.54,
    "mape_nd": 19.7,
    "señal_1d": "VENTA",
    "cambio_1d": -48.11,
    "color_1d": "#ef4444",
    "señal_5d": "VENTA",
    "cambio_5d": -48.68,
    "color_5d": "#ef4444",
    "señal_10d": "VENTA",
    "cambio_10d": -50.21,
    "color_10d": "#ef4444",
    "score": 3.3808,
    "img": "GOOGL.png",
    "es_cripto": false
  },
  {
    "ticker": "AMZN",
    "nombre": "Amazon",
    "precio_usd": 249.7,
    "precio_mxn": 4294.84,
    "mape_nd": 20.69,
    "señal_1d": "VENTA",
    "cambio_1d": -24.23,
    "color_1d": "#ef4444",
    "señal_5d": "VENTA",
    "cambio_5d": -31.82,
    "color_5d": "#ef4444",
    "señal_10d": "VENTA",
    "cambio_10d": -72.09,
    "color_10d": "#ef4444",
    "score": 3.227,
    "img": "AMZN.png",
    "es_cripto": false
  },
  {
    "ticker": "MSFT",
    "nombre": "Microsoft",
    "precio_usd": 420.26,
    "precio_mxn": 7228.47,
    "mape_nd": 21.79,
    "señal_1d": "VENTA",
    "cambio_1d": -16.85,
    "color_1d": "#ef4444",
    "señal_5d": "VENTA",
    "cambio_5d": -5.06,
    "color_5d": "#ef4444",
    "señal_10d": "VENTA",
    "cambio_10d": -16.44,
    "color_10d": "#ef4444",
    "score": 3.0713,
    "img": "MSFT.png",
    "es_cripto": false
  },
  {
    "ticker": "META",
    "nombre": "Meta Platforms",
    "precio_usd": 676.87,
    "precio_mxn": 11642.16,
    "mape_nd": 38.0,
    "señal_1d": "VENTA",
    "cambio_1d": -35.78,
    "color_1d": "#ef4444",
    "señal_5d": "VENTA",
    "cambio_5d": -40.5,
    "color_5d": "#ef4444",
    "señal_10d": "VENTA",
    "cambio_10d": -96.47,
    "color_10d": "#ef4444",
    "score": 1.7948,
    "img": "META.png",
    "es_cripto": false
  }
]